alcom/__init__.py
alcom/aligner.py
alcom/filemanager.py
alcom/run.py
alcom-1.3.0.dist-info/METADATA
alcom-1.3.0.dist-info/WHEEL
alcom-1.3.0.dist-info/entry_points.txt
alcom-1.3.0.dist-info/license
alcom-1.3.0.dist-info/top_level.txt
alcom-1.3.0.dist-info/RECORD
