Metadata-Version: 2.1
Name: alcom
Version: 1.3.0
Summary: UNKNOWN
Home-page: https://github.com/clowzed/alcom.git
Author: Miasnenko Dmitry
Author-email: clowzed.work@gmail.com
License: UNKNOWN
Platform: UNKNOWN
License-File: license
Requires-Dist: argparse
Requires-Dist: accessify
